README.md
setup.py
npn/__init__.py
npn/api.py
npn/libnpn.dll
npn/libnpn.so
npn.egg-info/PKG-INFO
npn.egg-info/SOURCES.txt
npn.egg-info/dependency_links.txt
npn.egg-info/top_level.txt
tests/test_npn.py